Spruce_ldap-0.1.3-py2.7-nspkg.pth
spruce/ldap/_services.py
spruce/ldap/_exc.py
spruce/ldap/_users.py
spruce/ldap/__init__.py
spruce/ldap/openldap/_services.py
spruce/ldap/openldap/__init__.py
spruce/ldap/testing/_services.py
spruce/ldap/testing/_users.py
spruce/ldap/testing/__init__.py
Spruce_ldap-0.1.3.dist-info/top_level.txt
Spruce_ldap-0.1.3.dist-info/RECORD
Spruce_ldap-0.1.3.dist-info/pydist.json
Spruce_ldap-0.1.3.dist-info/WHEEL
Spruce_ldap-0.1.3.dist-info/namespace_packages.txt
Spruce_ldap-0.1.3.dist-info/METADATA
Spruce_ldap-0.1.3.dist-info/entry_points.txt
Spruce_ldap-0.1.3.dist-info/DESCRIPTION.rst
