Metadata-Version: 2.0
Name: Spruce-ldap
Version: 0.1.3
Summary: Directory service interaction via LDAP
Home-page: UNKNOWN
Author: Ivan D Vasin
Author-email: nisavid@gmail.com
License: GNU LESSER GENERAL PUBLIC LICENSE
Requires-Dist: psutil
Requires-Dist: python-ldap
Requires-Dist: spruce-lang
Requires-Dist: spruce-pprint
Provides-Extra: openldap
